LICENSE
README.md
setup.py
mtmt/VERSION
mtmt/__init__.py
mtmt/mtmt.py
mtmt.egg-info/PKG-INFO
mtmt.egg-info/SOURCES.txt
mtmt.egg-info/dependency_links.txt
mtmt.egg-info/entry_points.txt
mtmt.egg-info/not-zip-safe
mtmt.egg-info/top_level.txt